dg/__init__.py
dg/dg.py
dataset_generator-0.0.1.dist-info/LICENSE
dataset_generator-0.0.1.dist-info/METADATA
dataset_generator-0.0.1.dist-info/WHEEL
dataset_generator-0.0.1.dist-info/top_level.txt
dataset_generator-0.0.1.dist-info/RECORD
